webix/__init__.py
webix-0.0.2.dist-info/METADATA
webix-0.0.2.dist-info/WHEEL
webix-0.0.2.dist-info/top_level.txt
webix-0.0.2.dist-info/RECORD
