Metadata-Version: 2.1
Name: webix
Version: 0.0.2
Summary: Linux for the web
Requires-Python: >=3.8
Requires-Dist: sphinx
